{
    "type": "FeatureCollection",
    "features": [
        {
            "type": "Feature",
            "properties": {
                "name": "Rilevazioni Sindbad"
            },
            "geometry": {
                "type": "Point",
                "coordinates": [
                    8.92624,
                    44.40799
                ]
            }
        }
    ]
}